attoworld/__init__.py
attoworld/attoworld_rs.cpython-38-aarch64-linux-gnu.so
attoworld/data/__init__.py
attoworld/data/complex_envelope.py
attoworld/data/complex_spectrum.py
attoworld/data/decorators.py
attoworld/data/file_io.py
attoworld/data/frog_data.py
attoworld/data/intensity_spectrum.py
attoworld/data/interop.py
attoworld/data/luna_result.py
attoworld/data/spectrogram.py
attoworld/data/spectrometer_calibration.py
attoworld/data/spectrometer_calibration_dataset.py
attoworld/data/waveform.py
attoworld/numeric/__init__.py
attoworld/numeric/atomic_units.py
attoworld/numeric/numeric.py
attoworld/personal/__init__.py
attoworld/personal/marco/UVSpectrumAnalysis.py
attoworld/personal/marco/VISSpectrumAnalysis.py
attoworld/personal/marco/__init__.py
attoworld/personal/marco/profileAndIntensity.py
attoworld/personal/marco/trace_handler.py
attoworld/personal/nick/__init__.py
attoworld/personal/nick/impulse_response.py
attoworld/personal/nick/nick.py
attoworld/personal/vlad/__init__.py
attoworld/plot/__init__.py
attoworld/plot/plot.py
attoworld/spectrum/__init__.py
attoworld/spectrum/calibration_data/7315273LS-Deuterium-Halogen_CC-VISNIR.lmp
attoworld/spectrum/calibration_data/7315273LS-Halogen_CC-VISNIR.lmp
attoworld/spectrum/calibration_data/MPQ_Atto_FROG_Ocean_HDX-XR.npz
attoworld/spectrum/calibration_data/MPQ_Atto_Maya_184_1101nm.npz
attoworld/spectrum/calibration_data/MPQ_Atto_Reso_Spectrometer_Marco.npz
attoworld/spectrum/calibration_data/Reso_Spectrometer_CalibrationCorrection.npz
attoworld/spectrum/calibration_data/__init__.py
attoworld/spectrum/spectrum.py
attoworld/wave/__init__.py
attoworld/wave/frog.py
attoworld/wave/time_frequency.py
attoworld/wave/wave.py
attoworld-2026.1.1.dist-info/METADATA
attoworld-2026.1.1.dist-info/WHEEL
attoworld-2026.1.1.dist-info/licenses/LICENSE
attoworld-2026.1.1.dist-info/RECORD
