Metadata-Version: 2.4
Name: attoworld
Version: 2026.1.1
Classifier: Programming Language :: Rust
Classifier: Programming Language :: Python :: Implementation :: CPython
Classifier: Programming Language :: Python :: Implementation :: PyPy
Requires-Dist: numpy
Requires-Dist: scipy
Requires-Dist: matplotlib
Requires-Dist: pyyaml
Requires-Dist: marimo
Requires-Dist: h5py
Requires-Dist: pandas
Requires-Dist: pywavelets
License-File: LICENSE
Summary: Tools from the Attosecond science group at the Max Planck Institute of Quantum Optics
Author-email: Nick Karpowicz <nicholas.karpowicz@mpq.mpg.de>
Requires-Python: >=3.8
Project-URL: Homepage, https://github.com/NickKarpowicz/Attoworld
Project-URL: Issues, https://github.com/NickKarpowicz/Attoworld/issues
